lib5c/__init__.py
lib5c/_version.py
lib5c/algorithms/__init__.py
lib5c/algorithms/convergency.py
lib5c/algorithms/correlation.py
lib5c/algorithms/determine_bins.py
lib5c/algorithms/donut_filters.py
lib5c/algorithms/donut_filters_legacy.py
lib5c/algorithms/enrichment.py
lib5c/algorithms/enrichment_legacy.py
lib5c/algorithms/expected.py
lib5c/algorithms/express.py
lib5c/algorithms/knight_ruiz.py
lib5c/algorithms/outliers.py
lib5c/algorithms/pca.py
lib5c/algorithms/qnorm.py
lib5c/algorithms/spline_normalization.py
lib5c/algorithms/thresholding.py
lib5c/algorithms/trimming.py
lib5c/algorithms/clustering/__init__.py
lib5c/algorithms/clustering/adjacency.py
lib5c/algorithms/clustering/enclave.py
lib5c/algorithms/clustering/greedy.py
lib5c/algorithms/clustering/knn.py
lib5c/algorithms/clustering/quasicontiguity.py
lib5c/algorithms/clustering/util.py
lib5c/algorithms/clustering/valley.py
lib5c/algorithms/distributions_legacy/__init__.py
lib5c/algorithms/distributions_legacy/fitting.py
lib5c/algorithms/distributions_legacy/variance.py
lib5c/algorithms/filtering/__init__.py
lib5c/algorithms/filtering/bin_bin_filtering.py
lib5c/algorithms/filtering/filter_functions.py
lib5c/algorithms/filtering/fragment_bin_filtering.py
lib5c/algorithms/filtering/fragment_fragment_filtering.py
lib5c/algorithms/filtering/unsmoothable_columns.py
lib5c/algorithms/filtering/util.py
lib5c/algorithms/variance/__init__.py
lib5c/algorithms/variance/combined.py
lib5c/algorithms/variance/cross_rep.py
lib5c/algorithms/variance/deviation.py
lib5c/algorithms/variance/estimate_variance.py
lib5c/algorithms/variance/local.py
lib5c/algorithms/variance/lognorm_dispersion.py
lib5c/algorithms/variance/mle.py
lib5c/algorithms/variance/nbinom_dispersion.py
lib5c/algorithms/variance_legacy/__init__.py
lib5c/algorithms/variance_legacy/grouping.py
lib5c/algorithms/variance_legacy/mle.py
lib5c/algorithms/variance_legacy/pvalues.py
lib5c/algorithms/variance_legacy/variance.py
lib5c-0.6.1.dist-info/LICENSE
lib5c-0.6.1.dist-info/METADATA
lib5c-0.6.1.dist-info/WHEEL
lib5c-0.6.1.dist-info/entry_points.txt
lib5c-0.6.1.dist-info/top_level.txt
lib5c-0.6.1.dist-info/RECORD
