Metadata-Version: 2.1
Name: lib5c
Version: 0.6.1
Summary: 5C analysis library
Home-page: https://bitbucket.org/creminslab/lib5c
Author: Thomas Gilgenast
Author-email: thomasgilgenast@gmail.com
License: UNKNOWN
Platform: UNKNOWN
Classifier: Development Status :: 5 - Production/Stable
Classifier: Environment :: Console
Classifier: Intended Audience :: Science/Research
Classifier: Programming Language :: Python :: 2
Classifier: Programming Language :: Python :: 2.7
Classifier: Programming Language :: Python :: 3
Classifier: Programming Language :: Python :: 3.6
Classifier: Topic :: Scientific/Engineering :: Bio-Informatics
Classifier: License :: OSI Approved :: MIT License
Requires-Dist: numpy (>=1.10.4)
Requires-Dist: scipy (>=0.16.1)
Requires-Dist: matplotlib (>=2.1.0)
Requires-Dist: pandas (>=0.18.0)
Requires-Dist: seaborn (>=0.8.0)
Requires-Dist: dill (>=0.2.5)
Requires-Dist: decorator (>=4.0.10)
Requires-Dist: luigi (>=2.1.1)
Requires-Dist: scikit-learn (>=0.17.1)
Requires-Dist: interlap (>=0.2.3)
Requires-Dist: powerlaw (>=1.4.3)
Requires-Dist: configparser (>=4.0.2) ; python_version < "3.2"
Requires-Dist: statsmodels (<=0.10.2,>=0.6.1) ; python_version < "3.5"
Requires-Dist: importlib-metadata (>=1.5.0) ; python_version < "3.8"
Requires-Dist: statsmodels (>=0.6.1) ; python_version >= "3.5"
Provides-Extra: bsub
Requires-Dist: bsub (>=0.3.5) ; extra == 'bsub'
Provides-Extra: complete
Requires-Dist: Sphinx (<2.2.1,>=1.7.2) ; extra == 'complete'
Requires-Dist: bsub (>=0.3.5) ; extra == 'complete'
Requires-Dist: flake8 (>=3.4.1) ; extra == 'complete'
Requires-Dist: iced (>=0.4.0) ; extra == 'complete'
Requires-Dist: ipykernel (<6.0,>=4.10.0) ; extra == 'complete'
Requires-Dist: m2r (>=0.2.1) ; extra == 'complete'
Requires-Dist: nbconvert (>=5.4.0) ; extra == 'complete'
Requires-Dist: nbformat (>=4.4.0) ; extra == 'complete'
Requires-Dist: nbstripout (>=0.3.5) ; extra == 'complete'
Requires-Dist: nose-exclude (>=0.5.0) ; extra == 'complete'
Requires-Dist: nose (>=1.3.7) ; extra == 'complete'
Requires-Dist: pyBigWig (>=0.3.4) ; extra == 'complete'
Requires-Dist: sphinx-rtd-theme (>=0.3.0) ; extra == 'complete'
Requires-Dist: sphinxcontrib-apidoc (>=0.3.0) ; extra == 'complete'
Provides-Extra: docs
Requires-Dist: Sphinx (<2.2.1,>=1.7.2) ; extra == 'docs'
Requires-Dist: sphinx-rtd-theme (>=0.3.0) ; extra == 'docs'
Requires-Dist: sphinxcontrib-apidoc (>=0.3.0) ; extra == 'docs'
Requires-Dist: m2r (>=0.2.1) ; extra == 'docs'
Provides-Extra: iced
Requires-Dist: iced (>=0.4.0) ; extra == 'iced'
Provides-Extra: pybigwig
Requires-Dist: pyBigWig (>=0.3.4) ; extra == 'pybigwig'
Provides-Extra: test
Requires-Dist: nose (>=1.3.7) ; extra == 'test'
Requires-Dist: nose-exclude (>=0.5.0) ; extra == 'test'
Requires-Dist: flake8 (>=3.4.1) ; extra == 'test'
Provides-Extra: tutorials
Requires-Dist: ipykernel (<6.0,>=4.10.0) ; extra == 'tutorials'
Requires-Dist: nbconvert (>=5.4.0) ; extra == 'tutorials'
Requires-Dist: nbformat (>=4.4.0) ; extra == 'tutorials'
Requires-Dist: nbstripout (>=0.3.5) ; extra == 'tutorials'
